azure_batch_extensions-9.0.0-py3.8-nspkg.pth
azext/batch/__init__.py
azext/batch/_file_utils.py
azext/batch/_pool_utils.py
azext/batch/_template_utils.py
azext/batch/batch_extensions_client.py
azext/batch/errors.py
azext/batch/version.py
azext/batch/models/__init__.py
azext/batch/models/_models.py
azext/batch/models/_models_py3.py
azext/batch/models/constants.py
azext/batch/operations/__init__.py
azext/batch/operations/file_operations.py
azext/batch/operations/job_operations.py
azext/batch/operations/pool_operations.py
azure_batch_extensions-9.0.0.dist-info/LICENSE.txt
azure_batch_extensions-9.0.0.dist-info/METADATA
azure_batch_extensions-9.0.0.dist-info/WHEEL
azure_batch_extensions-9.0.0.dist-info/namespace_packages.txt
azure_batch_extensions-9.0.0.dist-info/top_level.txt
azure_batch_extensions-9.0.0.dist-info/RECORD
