Metadata-Version: 2.1
Name: azure-batch-extensions
Version: 9.0.0
Summary: Microsoft Azure Batch Extended Features
Home-page: https://github.com/Azure/azure-batch-cli-extensions
Author: Microsoft Corporation
Author-email: azpycli@microsoft.com
License: MIT
Classifier: Development Status :: 4 - Beta
Classifier: Intended Audience :: Developers
Classifier: Intended Audience :: System Administrators
Classifier: Programming Language :: Python
Classifier: Programming Language :: Python :: 2
Classifier: Programming Language :: Python :: 2.7
Classifier: Programming Language :: Python :: 3
Classifier: Programming Language :: Python :: 3.4
Classifier: Programming Language :: Python :: 3.5
Classifier: Programming Language :: Python :: 3.6
Classifier: License :: OSI Approved :: MIT License
License-File: LICENSE.txt
Requires-Dist: msrestazure (<1,>=0.4.14)
Requires-Dist: azure-batch (<13,>=12.0)
Requires-Dist: azure-mgmt-batch (<17.0.0,>=16.2.0)
Requires-Dist: azure-storage-blob (>=1.1.0)
Requires-Dist: azure-mgmt-storage (<21,>=20.0)
Requires-Dist: pathlib (>=1.0.1) ; python_version<'3.4'
